huaweicloudsdkall/__init__.py
huaweicloudsdkall-3.1.184.dist-info/METADATA
huaweicloudsdkall-3.1.184.dist-info/WHEEL
huaweicloudsdkall-3.1.184.dist-info/licenses/LICENSE
huaweicloudsdkall-3.1.184.dist-info/RECORD
