Metadata-Version: 2.4
Name: huaweicloudsdkall
Version: 3.1.184
Summary: HuaweiCloud SDK Python All
Project-URL: Homepage, https://github.com/huaweicloud/huaweicloud-sdk-python-v3
Author-email: HuaweiCloud SDK <hwcloudsdk@huawei.com>
License-Expression: Apache-2.0
License-File: LICENSE
Keywords: all,huaweicloud,sdk
Classifier: Development Status :: 5 - Production/Stable
Classifier: Intended Audience :: Developers
Classifier: License :: OSI Approved :: Apache Software License
Classifier: Programming Language :: Python :: 3.6
Classifier: Programming Language :: Python :: 3.7
Classifier: Programming Language :: Python :: 3.8
Classifier: Programming Language :: Python :: 3.9
Classifier: Programming Language :: Python :: 3.10
Classifier: Programming Language :: Python :: 3.11
Classifier: Programming Language :: Python :: 3.12
Classifier: Topic :: Software Development
Requires-Python: >=3.6
Requires-Dist: huaweicloudsdkaad==3.1.184
Requires-Dist: huaweicloudsdkantiddos==3.1.184
Requires-Dist: huaweicloudsdkaom==3.1.184
Requires-Dist: huaweicloudsdkaos==3.1.184
Requires-Dist: huaweicloudsdkapig==3.1.184
Requires-Dist: huaweicloudsdkapm==3.1.184
Requires-Dist: huaweicloudsdkas==3.1.184
Requires-Dist: huaweicloudsdkasm==3.1.184
Requires-Dist: huaweicloudsdkastrozero==3.1.184
Requires-Dist: huaweicloudsdkbcc==3.1.184
Requires-Dist: huaweicloudsdkbcs==3.1.184
Requires-Dist: huaweicloudsdkbms==3.1.184
Requires-Dist: huaweicloudsdkbss==3.1.184
Requires-Dist: huaweicloudsdkbssintl==3.1.184
Requires-Dist: huaweicloudsdkcae==3.1.184
Requires-Dist: huaweicloudsdkcampusgo==3.1.184
Requires-Dist: huaweicloudsdkcbh==3.1.184
Requires-Dist: huaweicloudsdkcbr==3.1.184
Requires-Dist: huaweicloudsdkcbs==3.1.184
Requires-Dist: huaweicloudsdkcc==3.1.184
Requires-Dist: huaweicloudsdkcce==3.1.184
Requires-Dist: huaweicloudsdkccm==3.1.184
Requires-Dist: huaweicloudsdkcdm==3.1.184
Requires-Dist: huaweicloudsdkcdn==3.1.184
Requires-Dist: huaweicloudsdkces==3.1.184
Requires-Dist: huaweicloudsdkcfw==3.1.184
Requires-Dist: huaweicloudsdkclassroom==3.1.184
Requires-Dist: huaweicloudsdkclouddc==3.1.184
Requires-Dist: huaweicloudsdkcloudide==3.1.184
Requires-Dist: huaweicloudsdkcloudpond==3.1.184
Requires-Dist: huaweicloudsdkcloudrtc==3.1.184
Requires-Dist: huaweicloudsdkcloudtable==3.1.184
Requires-Dist: huaweicloudsdkcloudtest==3.1.184
Requires-Dist: huaweicloudsdkcoc==3.1.184
Requires-Dist: huaweicloudsdkcodeartsartifact==3.1.184
Requires-Dist: huaweicloudsdkcodeartsbuild==3.1.184
Requires-Dist: huaweicloudsdkcodeartscheck==3.1.184
Requires-Dist: huaweicloudsdkcodeartsdeploy==3.1.184
Requires-Dist: huaweicloudsdkcodeartsgovernance==3.1.184
Requires-Dist: huaweicloudsdkcodeartsinspector==3.1.184
Requires-Dist: huaweicloudsdkcodeartspipeline==3.1.184
Requires-Dist: huaweicloudsdkcodeartsrepo==3.1.184
Requires-Dist: huaweicloudsdkcodecraft==3.1.184
Requires-Dist: huaweicloudsdkconfig==3.1.184
Requires-Dist: huaweicloudsdkcpcs==3.1.184
Requires-Dist: huaweicloudsdkcph==3.1.184
Requires-Dist: huaweicloudsdkcpts==3.1.184
Requires-Dist: huaweicloudsdkcse==3.1.184
Requires-Dist: huaweicloudsdkcsms==3.1.184
Requires-Dist: huaweicloudsdkcss==3.1.184
Requires-Dist: huaweicloudsdkcts==3.1.184
Requires-Dist: huaweicloudsdkdas==3.1.184
Requires-Dist: huaweicloudsdkdataartsfabric==3.1.184
Requires-Dist: huaweicloudsdkdataartsfabricep==3.1.184
Requires-Dist: huaweicloudsdkdataartsstudio==3.1.184
Requires-Dist: huaweicloudsdkdbss==3.1.184
Requires-Dist: huaweicloudsdkdc==3.1.184
Requires-Dist: huaweicloudsdkdcc==3.1.184
Requires-Dist: huaweicloudsdkdcos==3.1.184
Requires-Dist: huaweicloudsdkdcs==3.1.184
Requires-Dist: huaweicloudsdkddm==3.1.184
Requires-Dist: huaweicloudsdkdds==3.1.184
Requires-Dist: huaweicloudsdkdeh==3.1.184
Requires-Dist: huaweicloudsdkdevstar==3.1.184
Requires-Dist: huaweicloudsdkdgc==3.1.184
Requires-Dist: huaweicloudsdkdis==3.1.184
Requires-Dist: huaweicloudsdkdlf==3.1.184
Requires-Dist: huaweicloudsdkdli==3.1.184
Requires-Dist: huaweicloudsdkdns==3.1.184
Requires-Dist: huaweicloudsdkdris==3.1.184
Requires-Dist: huaweicloudsdkdrs==3.1.184
Requires-Dist: huaweicloudsdkdsc==3.1.184
Requires-Dist: huaweicloudsdkdwr==3.1.184
Requires-Dist: huaweicloudsdkdws==3.1.184
Requires-Dist: huaweicloudsdkec==3.1.184
Requires-Dist: huaweicloudsdkecs==3.1.184
Requires-Dist: huaweicloudsdkedgesec==3.1.184
Requires-Dist: huaweicloudsdkeg==3.1.184
Requires-Dist: huaweicloudsdkeihealth==3.1.184
Requires-Dist: huaweicloudsdkeip==3.1.184
Requires-Dist: huaweicloudsdkelb==3.1.184
Requires-Dist: huaweicloudsdkeps==3.1.184
Requires-Dist: huaweicloudsdker==3.1.184
Requires-Dist: huaweicloudsdkesw==3.1.184
Requires-Dist: huaweicloudsdkevs==3.1.184
Requires-Dist: huaweicloudsdkfrs==3.1.184
Requires-Dist: huaweicloudsdkfunctiongraph==3.1.184
Requires-Dist: huaweicloudsdkga==3.1.184
Requires-Dist: huaweicloudsdkgaussdb==3.1.184
Requires-Dist: huaweicloudsdkgaussdbfornosql==3.1.184
Requires-Dist: huaweicloudsdkgaussdbforopengauss==3.1.184
Requires-Dist: huaweicloudsdkgeip==3.1.184
Requires-Dist: huaweicloudsdkges==3.1.184
Requires-Dist: huaweicloudsdkgsl==3.1.184
Requires-Dist: huaweicloudsdkhilens==3.1.184
Requires-Dist: huaweicloudsdkhss==3.1.184
Requires-Dist: huaweicloudsdkiam==3.1.184
Requires-Dist: huaweicloudsdkiamaccessanalyzer==3.1.184
Requires-Dist: huaweicloudsdkidentitycenter==3.1.184
Requires-Dist: huaweicloudsdkidentitycenteroidc==3.1.184
Requires-Dist: huaweicloudsdkidentitycenterportalapi==3.1.184
Requires-Dist: huaweicloudsdkidentitycenterscim==3.1.184
Requires-Dist: huaweicloudsdkidentitycenterstore==3.1.184
Requires-Dist: huaweicloudsdkidme==3.1.184
Requires-Dist: huaweicloudsdkidmeclassicapi==3.1.184
Requires-Dist: huaweicloudsdkiec==3.1.184
Requires-Dist: huaweicloudsdkief==3.1.184
Requires-Dist: huaweicloudsdkimage==3.1.184
Requires-Dist: huaweicloudsdkimagesearch==3.1.184
Requires-Dist: huaweicloudsdkims==3.1.184
Requires-Dist: huaweicloudsdkiotanalytics==3.1.184
Requires-Dist: huaweicloudsdkiotda==3.1.184
Requires-Dist: huaweicloudsdkiotdm==3.1.184
Requires-Dist: huaweicloudsdkiotedge==3.1.184
Requires-Dist: huaweicloudsdkivs==3.1.184
Requires-Dist: huaweicloudsdkkafka==3.1.184
Requires-Dist: huaweicloudsdkkms==3.1.184
Requires-Dist: huaweicloudsdkkoomessage==3.1.184
Requires-Dist: huaweicloudsdkkps==3.1.184
Requires-Dist: huaweicloudsdkkvs==3.1.184
Requires-Dist: huaweicloudsdklakeformation==3.1.184
Requires-Dist: huaweicloudsdklive==3.1.184
Requires-Dist: huaweicloudsdklts==3.1.184
Requires-Dist: huaweicloudsdkmapds==3.1.184
Requires-Dist: huaweicloudsdkmas==3.1.184
Requires-Dist: huaweicloudsdkmastudio==3.1.184
Requires-Dist: huaweicloudsdkmeeting==3.1.184
Requires-Dist: huaweicloudsdkmetastudio==3.1.184
Requires-Dist: huaweicloudsdkmoderation==3.1.184
Requires-Dist: huaweicloudsdkmpc==3.1.184
Requires-Dist: huaweicloudsdkmrs==3.1.184
Requires-Dist: huaweicloudsdkmsgsms==3.1.184
Requires-Dist: huaweicloudsdkmssi==3.1.184
Requires-Dist: huaweicloudsdknat==3.1.184
Requires-Dist: huaweicloudsdknlp==3.1.184
Requires-Dist: huaweicloudsdkobs==3.1.184
Requires-Dist: huaweicloudsdkocr==3.1.184
Requires-Dist: huaweicloudsdkoctopus==3.1.184
Requires-Dist: huaweicloudsdkoms==3.1.184
Requires-Dist: huaweicloudsdkoptverse==3.1.184
Requires-Dist: huaweicloudsdkorganizations==3.1.184
Requires-Dist: huaweicloudsdkorgid==3.1.184
Requires-Dist: huaweicloudsdkoroas==3.1.184
Requires-Dist: huaweicloudsdkosm==3.1.184
Requires-Dist: huaweicloudsdkpangulargemodels==3.1.184
Requires-Dist: huaweicloudsdkprojectman==3.1.184
Requires-Dist: huaweicloudsdkrabbitmq==3.1.184
Requires-Dist: huaweicloudsdkram==3.1.184
Requires-Dist: huaweicloudsdkrds==3.1.184
Requires-Dist: huaweicloudsdkres==3.1.184
Requires-Dist: huaweicloudsdkrfs==3.1.184
Requires-Dist: huaweicloudsdkrgc==3.1.184
Requires-Dist: huaweicloudsdkrms==3.1.184
Requires-Dist: huaweicloudsdkrocketmq==3.1.184
Requires-Dist: huaweicloudsdkroma==3.1.184
Requires-Dist: huaweicloudsdksa==3.1.184
Requires-Dist: huaweicloudsdkscm==3.1.184
Requires-Dist: huaweicloudsdksdrs==3.1.184
Requires-Dist: huaweicloudsdksecmaster==3.1.184
Requires-Dist: huaweicloudsdkservicestage==3.1.184
Requires-Dist: huaweicloudsdksfsturbo==3.1.184
Requires-Dist: huaweicloudsdksis==3.1.184
Requires-Dist: huaweicloudsdksmn==3.1.184
Requires-Dist: huaweicloudsdksmnglobal==3.1.184
Requires-Dist: huaweicloudsdksms==3.1.184
Requires-Dist: huaweicloudsdksmsapi==3.1.184
Requires-Dist: huaweicloudsdksts==3.1.184
Requires-Dist: huaweicloudsdkswr==3.1.184
Requires-Dist: huaweicloudsdktics==3.1.184
Requires-Dist: huaweicloudsdktms==3.1.184
Requires-Dist: huaweicloudsdkucs==3.1.184
Requires-Dist: huaweicloudsdkugo==3.1.184
Requires-Dist: huaweicloudsdkvas==3.1.184
Requires-Dist: huaweicloudsdkvcm==3.1.184
Requires-Dist: huaweicloudsdkversatile==3.1.184
Requires-Dist: huaweicloudsdkvod==3.1.184
Requires-Dist: huaweicloudsdkvpc==3.1.184
Requires-Dist: huaweicloudsdkvpcep==3.1.184
Requires-Dist: huaweicloudsdkvpn==3.1.184
Requires-Dist: huaweicloudsdkwaf==3.1.184
Requires-Dist: huaweicloudsdkworkspace==3.1.184
Requires-Dist: huaweicloudsdkworkspaceapp==3.1.184
